pandora_app/__init__.py
pandora_app/app_config.json
pandora_app/launch_app.py
pandora_app/pandora_app.py
pandora_app/quick_help.md
pandora_app/.streamlit/config.toml
pandora_app/.streamlit/credentials.toml
pandora_app/app_images/pandora-avatar.png
pandora_app/app_images/pandora-image.png
pandora_app/app_images/pandora_demo.jpg
pandora_app/app_images/pandora_logo.png
pandora_app/app_images/system-avatar.png
pandora_app/app_images/user-avatar.png
pandora_app/tools/__init__.py
pandora_app/tools/crypto.py
pandora_app/tools/custom_code_editor.py
pandora_app/tools/google_search.py
pandora_app/tools/restrict_module.py
pandora_app/tools/tex_to_pdf.py
pandora_app/tools/whisperSTT.py
pandora_app/tools/whisper_stt.py
pandora_app-0.0.49.dist-info/LICENSE
pandora_app-0.0.49.dist-info/METADATA
pandora_app-0.0.49.dist-info/WHEEL
pandora_app-0.0.49.dist-info/entry_points.txt
pandora_app-0.0.49.dist-info/top_level.txt
pandora_app-0.0.49.dist-info/RECORD
