Metadata-Version: 2.1
Name: pandora_app
Version: 0.0.49
Summary: Streamlit interface for the pandora_ai project.
Home-page: https://github.com/B4PT0R/pandora_app
Author: Baptiste Ferrand
Author-email: bferrand.maths@gmail.com
Classifier: Programming Language :: Python :: 3
Classifier: License :: OSI Approved :: MIT License
Classifier: Operating System :: OS Independent
License-File: LICENSE
Requires-Dist: pandora-ai
Requires-Dist: streamlit-stacker
Requires-Dist: firebase-user
Requires-Dist: google-api-python-client
Requires-Dist: gTTS
Requires-Dist: objdict-bf
Requires-Dist: python-dotenv
Requires-Dist: seleniumbase
Requires-Dist: spotipy
Requires-Dist: streamlit
Requires-Dist: streamlit-code-editor
Requires-Dist: streamlit-input-box
Requires-Dist: streamlit-mic-recorder
Requires-Dist: streamlit-TTS
Requires-Dist: matplotlib
Requires-Dist: numpy
Requires-Dist: seaborn
Requires-Dist: pandas
Requires-Dist: graphviz
Requires-Dist: altair
Requires-Dist: plotly
Requires-Dist: bokeh
Requires-Dist: pydeck
Requires-Dist: scipy
Requires-Dist: sympy
Requires-Dist: scikit-learn
Requires-Dist: vega-datasets
